rikai_sklearn/__init__.py
rikai_sklearn/mlflow.py
rikai_sklearn/numpy.py
rikai_sklearn/models/__init__.py
rikai_sklearn/models/classifier.py
rikai_sklearn/models/cluster.py
rikai_sklearn/models/regressor.py
rikai_sklearn/models/transformer.py
rikai_sklearn-0.1.1.dist-info/METADATA
rikai_sklearn-0.1.1.dist-info/WHEEL
rikai_sklearn-0.1.1.dist-info/namespace_packages.txt
rikai_sklearn-0.1.1.dist-info/top_level.txt
rikai_sklearn-0.1.1.dist-info/RECORD
