Metadata-Version: 2.1
Name: rikai-sklearn
Version: 0.1.1
License: Apache License, Version 2.0
Requires-Python: >=3.7
Requires-Dist: rikai (==0.1.14)
Requires-Dist: scikit-learn
